{"fields":[{"id":"a","label":"City Name","type":"string"},{"id":"b","label":"Buses (2017-18)","type":"string"},{"id":"c","label":"2016-17","type":"string"},{"id":"d","label":"2015-16","type":"string"},{"id":"e","label":"2014-15","type":"string"},{"id":"f","label":"Light Motor Vehicles (2017-18)","type":"string"},{"id":"g","label":"2016-17","type":"string"},{"id":"h","label":"2015-16","type":"string"},{"id":"i","label":"2014-15","type":"string"},{"id":"j","label":"Goods Carrier Vehicles (2017-18)","type":"string"},{"id":"k","label":"2016-17","type":"string"},{"id":"l","label":"2015-16","type":"string"},{"id":"m","label":"2014-15","type":"string"},{"id":"n","label":"Two-Wheeler Vehicles (2017-18)","type":"string"},{"id":"o","label":"2016-17","type":"string"},{"id":"p","label":"2015-16","type":"string"},{"id":"q","label":"2014-15","type":"string"},{"id":"r","label":"Four-Wheeler Vehicles (2017-18)","type":"string"},{"id":"s","label":"2016-17","type":"string"},{"id":"t","label":"2015-16","type":"string"},{"id":"u","label":"2014-15","type":"string"},{"id":"v","label":"Miscellaneous (2017-18)","type":"string"},{"id":"w","label":"2016-17","type":"string"},{"id":"x","label":"2015-16","type":"string"},{"id":"y","label":"2014-15","type":"string"}],"data":null}